zotion/__init__.py
zotion/client.py
zotion-0.1.1.dist-info/WHEEL
zotion-0.1.1.dist-info/METADATA
zotion-0.1.1.dist-info/RECORD
